LICENSE
MANIFEST.in
README.md
package.json
setup.py
tests/test_usage.py
threejs_dash/ThreejsDash.py
threejs_dash/__init__.py
threejs_dash/_imports_.py
threejs_dash/metadata.json
threejs_dash/package-info.json
threejs_dash/threejs_dash.min.js
threejs_dash/threejs_dash.min.js.map
threejs_dash.egg-info/PKG-INFO
threejs_dash.egg-info/SOURCES.txt
threejs_dash.egg-info/dependency_links.txt
threejs_dash.egg-info/top_level.txt