Metadata-Version: 2.1
Name: threejs_dash
Version: 0.0.1
Summary: Project Description
Author: mads kristensen <madskris@proton.me>
License: MIT
Classifier: Framework :: Dash
License-File: LICENSE
